google/cloud/domains/__init__.py
google/cloud/domains/gapic_version.py
google/cloud/domains/py.typed
google/cloud/domains_v1/__init__.py
google/cloud/domains_v1/gapic_metadata.json
google/cloud/domains_v1/gapic_version.py
google/cloud/domains_v1/py.typed
google/cloud/domains_v1/services/__init__.py
google/cloud/domains_v1/services/domains/__init__.py
google/cloud/domains_v1/services/domains/async_client.py
google/cloud/domains_v1/services/domains/client.py
google/cloud/domains_v1/services/domains/pagers.py
google/cloud/domains_v1/services/domains/transports/__init__.py
google/cloud/domains_v1/services/domains/transports/base.py
google/cloud/domains_v1/services/domains/transports/grpc.py
google/cloud/domains_v1/services/domains/transports/grpc_asyncio.py
google/cloud/domains_v1/services/domains/transports/rest.py
google/cloud/domains_v1/services/domains/transports/rest_base.py
google/cloud/domains_v1/types/__init__.py
google/cloud/domains_v1/types/domains.py
google/cloud/domains_v1beta1/__init__.py
google/cloud/domains_v1beta1/gapic_metadata.json
google/cloud/domains_v1beta1/gapic_version.py
google/cloud/domains_v1beta1/py.typed
google/cloud/domains_v1beta1/services/__init__.py
google/cloud/domains_v1beta1/services/domains/__init__.py
google/cloud/domains_v1beta1/services/domains/async_client.py
google/cloud/domains_v1beta1/services/domains/client.py
google/cloud/domains_v1beta1/services/domains/pagers.py
google/cloud/domains_v1beta1/services/domains/transports/__init__.py
google/cloud/domains_v1beta1/services/domains/transports/base.py
google/cloud/domains_v1beta1/services/domains/transports/grpc.py
google/cloud/domains_v1beta1/services/domains/transports/grpc_asyncio.py
google/cloud/domains_v1beta1/services/domains/transports/rest.py
google/cloud/domains_v1beta1/services/domains/transports/rest_base.py
google/cloud/domains_v1beta1/types/__init__.py
google/cloud/domains_v1beta1/types/domains.py
google_cloud_domains-1.11.0.dist-info/licenses/LICENSE
google_cloud_domains-1.11.0.dist-info/METADATA
google_cloud_domains-1.11.0.dist-info/WHEEL
google_cloud_domains-1.11.0.dist-info/top_level.txt
google_cloud_domains-1.11.0.dist-info/RECORD
